pdbUtils/__init__.py
pdbUtils/pdbUtils.py
pdbUtils-2024.0.1.dist-info/METADATA
pdbUtils-2024.0.1.dist-info/WHEEL
pdbUtils-2024.0.1.dist-info/top_level.txt
pdbUtils-2024.0.1.dist-info/RECORD
