Metadata-Version: 2.1
Name: pdbUtils
Version: 2024.0.1
Summary: A small python module that can parse PDB files as pandas DataFrames.
Home-page: https://github.com/ESPhoenix/pdbUtils
Download-URL: https://pypi.org/project/pdbUtils
Author: Eugene Shrimpton-Phoenix
Author-email: Eugene Shrimpton-Phoenix <eshrimpt@ed.ac.uk>
Maintainer: Marta Chronowska
Maintainer-email: Marta Chronowska <mchrnwsk@gmail.com>
License: GPLv3
Project-URL: Source, https://github.com/ESPhoenix/pdbUtils
Requires-Python: >=3.7
Requires-Dist: pandas
